[
{"user_name":"Ksxkwcbq Axfu","user_email":"Ksxkwcbq@sokolov.net","user_password":"4k101H","user_phone":"670523110005","incorrect_user_name":"","incorrect_user_email":"","incorrect_user_password":"ym","incorrect_user_phone":"092","login":"Ksxkwcbq@sokolov.net","password":"4k101H","incorrect_login":"Yedbcbc@@@derfd..ru","incorrect_password":"anwj","new_user_email":"Focxccpi@sokolov.net","new_user_password":"8sns15d635DM","new_user_name":"Ucohjsg Vxgssiitt","new_user_phone":"387071292549187","new_user_birth_date":1170467689,"new_user_gender":"MALE","new_user_news":true,"new_user_notifications":false,"incorrect_new_user_email":"Yedbcbc@@@derfd..ru","incorrect_new_user_password":"ljctk","incorrect_new_user_name":32619,"incorrect_new_user_phone":"18193291","incorrect_new_user_birth_date":"20-12-1987","incorrect_new_user_gender":"mefale","incorrect_new_user_news":"false","incorrect_new_user_notifications":"false","barcode":"1011293005954","article":"721069","incorrect_barcode":"Dcd-df$","incorrect_article":"fgffPd~.","non_exists_barcode":"3511051984205"},
{"user_name":"Eun Cvzxocxh","user_email":"Eun@sokolov.net","user_password":"ta85740kBPW3","user_phone":"957365677710018","incorrect_user_name":59149,"incorrect_user_email":"Yedbcbc@@@derfd..ru","incorrect_user_password":"","incorrect_user_phone":"7057166","login":"Eun@sokolov.net","password":"ta85740kBPW3","incorrect_login":"","incorrect_password":"be","new_user_email":"Nqohnmul@sokolov.net","new_user_password":"6F9Bi14H589","new_user_name":"Mba Hjrfshp","new_user_phone":"1007193767","new_user_birth_date":1331856481,"new_user_gender":"FEMALE","new_user_news":false,"new_user_notifications":false,"incorrect_new_user_email":"Yedbcbc@@@derfd..ru","incorrect_new_user_password":"tml","incorrect_new_user_name":50730,"incorrect_new_user_phone":"07160502","incorrect_new_user_birth_date":"20-12-1987","incorrect_new_user_gender":"mefale","incorrect_new_user_news":"false","incorrect_new_user_notifications":"false","barcode":"1011294010681","article":"91020172","incorrect_barcode":"Dcd-df$","incorrect_article":"fgffPd~.","non_exists_barcode":"2235253799007"},
{"user_name":"Wzz Yxql","user_email":"Wzz@sokolov.net","user_password":"8M0Ys54","user_phone":"22734156377","incorrect_user_name":"","incorrect_user_email":"Yedbcbc@@@derfd..ru","incorrect_user_password":"ao","incorrect_user_phone":"8746","login":"Wzz@sokolov.net","password":"8M0Ys54","incorrect_login":"","incorrect_password":"t","new_user_email":"Frbahcoe@sokolov.net","new_user_password":"E5Ch377gh442","new_user_name":"Eomvrmrmv Lka","new_user_phone":"03779472890","new_user_birth_date":1299028289,"new_user_gender":"FEMALE","new_user_news":false,"new_user_notifications":false,"incorrect_new_user_email":"Yedbcbc@@@derfd..ru","incorrect_new_user_password":"krp","incorrect_new_user_name":"","incorrect_new_user_phone":"99940930","incorrect_new_user_birth_date":"20-12-1987","incorrect_new_user_gender":"mefale","incorrect_new_user_news":"false","incorrect_new_user_notifications":"false","barcode":"1011261003883","article":"91010321","incorrect_barcode":"Dcd-df$","incorrect_article":"fgffPd~.","non_exists_barcode":"4355446894653"},
{"user_name":"Zxghbgh Mxffuaesg","user_email":"Zxghbgh@sokolov.net","user_password":"R04DsR61","user_phone":"5048570671025","incorrect_user_name":"","incorrect_user_email":"Yedbcbc@@@derfd..ru","incorrect_user_password":"","incorrect_user_phone":"57","login":"Zxghbgh@sokolov.net","password":"R04DsR61","incorrect_login":"Yedbcbc@@@derfd..ru","incorrect_password":"o","new_user_email":"Thwyqtyrk@sokolov.net","new_user_password":"057E518f5","new_user_name":"Ewiaau Cvbsb","new_user_phone":"69749311064","new_user_birth_date":1102997118,"new_user_gender":"FEMALE","new_user_news":true,"new_user_notifications":false,"incorrect_new_user_email":"Yedbcbc@@@derfd..ru","incorrect_new_user_password":"oj","incorrect_new_user_name":"","incorrect_new_user_phone":"11","incorrect_new_user_birth_date":"20-12-1987","incorrect_new_user_gender":"mefale","incorrect_new_user_news":"false","incorrect_new_user_notifications":"false","barcode":"1011273019025","article":"91020317","incorrect_barcode":"Dcd-df$","incorrect_article":"fgffPd~.","non_exists_barcode":"8850149432615"},
{"user_name":"Necsqriqde Zimztb","user_email":"Necsqriqde@sokolov.net","user_password":"VX2yjvZ80pF8","user_phone":"97380454247477","incorrect_user_name":"","incorrect_user_email":"Yedbcbc@@@derfd..ru","incorrect_user_password":"ulfd","incorrect_user_phone":"58100213","login":"Necsqriqde@sokolov.net","password":"VX2yjvZ80pF8","incorrect_login":"Yedbcbc@@@derfd..ru","incorrect_password":"","new_user_email":"Ipavjo@sokolov.net","new_user_password":"r6w8944","new_user_name":"Qkza Zffm","new_user_phone":"17034144956175","new_user_birth_date":1123335429,"new_user_gender":"FEMALE","new_user_news":true,"new_user_notifications":true,"incorrect_new_user_email":"","incorrect_new_user_password":"aa","incorrect_new_user_name":"","incorrect_new_user_phone":"26818030","incorrect_new_user_birth_date":"20-12-1987","incorrect_new_user_gender":"mefale","incorrect_new_user_news":"false","incorrect_new_user_notifications":"false","barcode":"1011261006907","article":"91020612","incorrect_barcode":"Dcd-df$","incorrect_article":"fgffPd~.","non_exists_barcode":"1644749900825"},
{"user_name":"Kmjct Moqjxhfr","user_email":"Kmjct@sokolov.net","user_password":"HCzT171P012k","user_phone":"215131977708","incorrect_user_name":53666,"incorrect_user_email":"Yedbcbc@@@derfd..ru","incorrect_user_password":"","incorrect_user_phone":"64","login":"Kmjct@sokolov.net","password":"HCzT171P012k","incorrect_login":"","incorrect_password":"eayr","new_user_email":"Hitk@sokolov.net","new_user_password":"yFgPUbt38S92","new_user_name":"Kmrvvhjeg Qbhmx","new_user_phone":"314827578781549","new_user_birth_date":1425244335,"new_user_gender":"MALE","new_user_news":true,"new_user_notifications":true,"incorrect_new_user_email":"Yedbcbc@@@derfd..ru","incorrect_new_user_password":"eiwux","incorrect_new_user_name":1832,"incorrect_new_user_phone":"94611414","incorrect_new_user_birth_date":"20-12-1987","incorrect_new_user_gender":"mefale","incorrect_new_user_news":"false","incorrect_new_user_notifications":"false","barcode":"1011264000636","article":"140011","incorrect_barcode":"Dcd-df$","incorrect_article":"fgffPd~.","non_exists_barcode":"4862663092778"},
{"user_name":"Oaxaah Uoqxfihe","user_email":"Oaxaah@sokolov.net","user_password":"5Fx34h6","user_phone":"94723694811259","incorrect_user_name":"","incorrect_user_email":"","incorrect_user_password":"hnnvi","incorrect_user_phone":"313","login":"Oaxaah@sokolov.net","password":"5Fx34h6","incorrect_login":"Yedbcbc@@@derfd..ru","incorrect_password":"rl","new_user_email":"Mefzu@sokolov.net","new_user_password":"461NT55PRVo","new_user_name":"Hnois Iesyabpk","new_user_phone":"46663794940","new_user_birth_date":1447928943,"new_user_gender":"MALE","new_user_news":true,"new_user_notifications":true,"incorrect_new_user_email":"Yedbcbc@@@derfd..ru","incorrect_new_user_password":"g","incorrect_new_user_name":26250,"incorrect_new_user_phone":"28219","incorrect_new_user_birth_date":"20-12-1987","incorrect_new_user_gender":"mefale","incorrect_new_user_news":"false","incorrect_new_user_notifications":"false","barcode":"1010224021667","article":"91020612","incorrect_barcode":"Dcd-df$","incorrect_article":"fgffPd~.","non_exists_barcode":"9077781290752"},
{"user_name":"Qxicyj Pykldxw","user_email":"Qxicyj@sokolov.net","user_password":"149091lGN3y1","user_phone":"888979395225021","incorrect_user_name":"","incorrect_user_email":"Yedbcbc@@@derfd..ru","incorrect_user_password":"dnqua","incorrect_user_phone":"39042428","login":"Qxicyj@sokolov.net","password":"149091lGN3y1","incorrect_login":"Yedbcbc@@@derfd..ru","incorrect_password":"s","new_user_email":"Vhxwyphtr@sokolov.net","new_user_password":"2121j7","new_user_name":"Qadhel Fmay","new_user_phone":"3257526320","new_user_birth_date":1131378967,"new_user_gender":"FEMALE","new_user_news":true,"new_user_notifications":true,"incorrect_new_user_email":"","incorrect_new_user_password":"yjdyd","incorrect_new_user_name":53684,"incorrect_new_user_phone":"59063","incorrect_new_user_birth_date":"20-12-1987","incorrect_new_user_gender":"mefale","incorrect_new_user_news":"false","incorrect_new_user_notifications":"false","barcode":"1011224003370","article":"91020598","incorrect_barcode":"Dcd-df$","incorrect_article":"fgffPd~.","non_exists_barcode":"4242942997165"},
{"user_name":"Yodwljib Axx","user_email":"Yodwljib@sokolov.net","user_password":"7908c486332o","user_phone":"95656906695653","incorrect_user_name":54021,"incorrect_user_email":"","incorrect_user_password":"lbog","incorrect_user_phone":"586","login":"Yodwljib@sokolov.net","password":"7908c486332o","incorrect_login":"","incorrect_password":"z","new_user_email":"Ksblsa@sokolov.net","new_user_password":"G93x267808","new_user_name":"Iya Qbfzhdayk","new_user_phone":"7206188326715","new_user_birth_date":1022560371,"new_user_gender":"FEMALE","new_user_news":true,"new_user_notifications":true,"incorrect_new_user_email":"","incorrect_new_user_password":"qfdi","incorrect_new_user_name":23401,"incorrect_new_user_phone":"2135","incorrect_new_user_birth_date":"20-12-1987","incorrect_new_user_gender":"mefale","incorrect_new_user_news":"false","incorrect_new_user_notifications":"false","barcode":"1011234015486","article":"91030186","incorrect_barcode":"Dcd-df$","incorrect_article":"fgffPd~.","non_exists_barcode":"5007162353023"},
{"user_name":"Cjitmuy Jlm","user_email":"Cjitmuy@sokolov.net","user_password":"iLe91g","user_phone":"045809761032268","incorrect_user_name":"","incorrect_user_email":"Yedbcbc@@@derfd..ru","incorrect_user_password":"","incorrect_user_phone":"08506","login":"Cjitmuy@sokolov.net","password":"iLe91g","incorrect_login":"","incorrect_password":"zdt","new_user_email":"Kway@sokolov.net","new_user_password":"8XI25PDM1","new_user_name":"Ghfivq Lbyusqm","new_user_phone":"413402534981892","new_user_birth_date":1111659333,"new_user_gender":"FEMALE","new_user_news":false,"new_user_notifications":true,"incorrect_new_user_email":"Yedbcbc@@@derfd..ru","incorrect_new_user_password":"pza","incorrect_new_user_name":50621,"incorrect_new_user_phone":"9016","incorrect_new_user_birth_date":"20-12-1987","incorrect_new_user_gender":"mefale","incorrect_new_user_news":"false","incorrect_new_user_notifications":"false","barcode":"1011241003483","article":"750001","incorrect_barcode":"Dcd-df$","incorrect_article":"fgffPd~.","non_exists_barcode":"7227612961013"}
]
